metaflow_extensions/scatter3d/__init__.py
metaflow_extensions/scatter3d/plugins/cards/scatter3d/__init__.py
metaflow_extensions/scatter3d/plugins/cards/scatter3d/base.html
metaflow_extensions/scatter3d/plugins/cards/scatter3d/assets/scatter.js
metaflow_extensions/scatter3d/plugins/cards/scatter3d/assets/three.js
metaflow_card_scatter3d-0.0.1.dist-info/LICENSE
metaflow_card_scatter3d-0.0.1.dist-info/METADATA
metaflow_card_scatter3d-0.0.1.dist-info/WHEEL
metaflow_card_scatter3d-0.0.1.dist-info/top_level.txt
metaflow_card_scatter3d-0.0.1.dist-info/RECORD
